commitmessagegenerator/__init__.py
commitmessagegenerator/cli.py
commitmessagegenerator/configure.py
commitmessagegenerator/generator.py
commitmessagegenerator-1.5.0.dist-info/licenses/LICENSE
commitmessagegenerator-1.5.0.dist-info/METADATA
commitmessagegenerator-1.5.0.dist-info/WHEEL
commitmessagegenerator-1.5.0.dist-info/entry_points.txt
commitmessagegenerator-1.5.0.dist-info/top_level.txt
commitmessagegenerator-1.5.0.dist-info/RECORD
