Metadata-Version: 2.4
Name: commitmessagegenerator
Version: 1.5.0
Summary: Generate commit messages with AI (Google Gemini) automatically using `git diff`.
Author-email: Gabriel Terceiro <gcarolinoterceiro@gmail.com>
License: MIT
License-File: LICENSE
Requires-Dist: google-genai==1.20.0
Requires-Dist: GitPython==3.1.44
Requires-Dist: python-dotenv==1.1.0
Dynamic: license-file
